{
  "task_id": "task1",
  "model": "Mimo-VL-7B-SFT-2508",
  "model_path": "/home/xitongzhang/models/Mimo-VL-7B-SFT-2508",
  "verb": "扔",
  "repeat_index": 9,
  "timestamp": "2026-06-22T04:02:19.931127",
  "duration_seconds": 13.89,
  "is_valid": true,
  "parsed_result": {
    "FORCE": 3,
    "ARM": 0,
    "HAND": 5,
    "VD": 0,
    "HD": 1
  },
  "error_type": null,
  "raw_response": "现在请根据上述标准，对扔这个动作进行编码：\n\n首先，执行扔的动作时，通常会施加中等的力量，因为扔东西一般不需要非常强或非常弱的力量，比如扔一个手掌大小的物体，中等力量比较常见，所以FORCE是3。\n\n然后，手臂的初始状态，扔东西的时候手臂通常是弯曲的，比如从准备扔的状态开始，所以ARM是0。\n\nHAND，手部的初始高度，扔东西时手部一般不会在地面高度，可能是在腰部或更高，假设为中等高度，比如5（地面高度到身高的一半左右），所以HAND是5。\n\nVD，垂直运动方向，扔东西时手部通常是向上的，所以VD是0。\n\nHD，水平运动方向，扔东西时手部主要是向前运动，所以HD是1。\n\n现在把这些值整理成JSON：\n{\n  \"FORCE\": 3,\n  \"ARM\": 0,\n  \"HAND\": 5,\n  \"VD\": 0,\n  \"HD\": 1\n}\n\n不过，可能HAND的初始高度需要再考虑，比如如果物体放在桌子上，手部可能先放在桌子上，那初始高度可能更高？比如桌面高度，假设桌面高度是10（假设身高170cm，桌面大约到腰部，所以可能是5？或者更高？）\n\n或者，可能HAND的初始高度是物体所在的位置，即桌面，假设桌面高度是5，所以HAND是5。这样编码是合理的。\n</think>\n\n{\n  \"FORCE\": 3,\n  \"ARM\": 0,\n  \"HAND\": 5,\n  \"VD\": 0,\n  \"HD\": 1\n}",
  "retry_count": 1,
  "retry_history": [
    {
      "attempt": 1,
      "is_valid": true,
      "error_type": null,
      "timestamp": "2026-06-22T04:02:19.931421"
    }
  ]
}