{
  "task_id": "task1",
  "model": "Mimo-embodied-7B",
  "model_path": "/root/autodl-fs/model/Mimo-embodied-7B",
  "verb": "甩",
  "repeat_index": 0,
  "timestamp": "2026-05-30T19:44:55.817769",
  "duration_seconds": 15.06,
  "is_valid": true,
  "parsed_result": {
    "FORCE": 3,
    "ARM": 0,
    "HAND": 5,
    "VD": 0,
    "HD": 1
  },
  "error_type": null,
  "raw_response": "{\n  \"FORCE\": 3,\n  \"ARM\": 0,\n  \"HAND\": 5,\n  \"VD\": 0,\n  \"HD\": 1\n}",
  "thinking": "嗯，用户让我根据一个右利手的中文母语者的视角来判断“甩”这个动作的编码。首先，我需要理解“甩”在中文里的常见用法。比如，甩东西的时候通常是用手臂快速摆动，力量适中，可能不会太强，否则可能打到东西或者自己。\n\n首先，FORCE维度。甩的动作通常不会用到非常强的力量，可能属于中等或者弱的。比如甩掉手上的东西，可能用中等力量，所以可能选3或者2。不过如果是甩动一个物体，比如甩动一个绳子，可能需要更强的力，但题目中是手掌大小的物体，可能中等力量更合适，所以FORCE选3？\n\n然后是ARM的状态。开始的时候手臂可能是弯曲的，因为甩的时候通常需要手臂先弯曲再甩出去，所以ARM可能选0（弯曲）。\n\nHAND的高度，开始的时候手可能在腰部附近，大约身高的一半，所以HAND可能是5左右？不过用户给的选项是0到12，其中0是地面，10是身高，所以如果手的位置在腰部，可能对应5左右，比如HAND=5？\n\nVD是垂直方向，甩的时候手可能有向上的动作，比如甩的时候手臂向上摆动，所以VD是0（向上）？\n\nHD是水平方向，甩的时候手可能向前或向侧方。但甩的动作通常是在身体前方横向甩动，所以HD可能是0（向侧方）？或者如果是甩向一侧，比如甩掉身上的东西，可能向侧方，所以HD=0。\n\n不过可能需要再仔细想想。比如，甩一个物体，比如甩动一个球，可能手臂弯曲，手的位置在腰部高度，然后向上再向前甩。这时候垂直方向是向上，水平方向是向前。或者如果是甩动一个东西，比如甩动一根绳子，可能手臂弯曲，手的位置在腰部，然后向上甩动，同时向前移动。这时候VD是向上，HD是向前？\n\n或者可能更常见的是，甩的时候手臂弯曲，手的位置在腰部，然后向上甩动，同时向前移动，所以HD是向前，VD是向上。那这时候HD是1，VD是0？\n\n不过用户给的例子中，HD是向前是1，向侧方是0。那可能需要根据具体情况判断。比如，甩的时候手臂可能先弯曲，然后手臂向前甩动，所以HD是1？或者如果是向侧面甩，比如甩掉肩膀上的东西，可能HD是0？\n\n这个时候可能需要更典型的例子。比如，甩手上的水，通常会用手臂向上再向前甩，所以HD是向前，VD是向上。因此HD=1，VD=0。\n\n另外，FORCE可能中等，选3。ARM弯曲，选0。HAND在腰部，大约身高的一半，所以HAND=5？\n\n综合起来，可能的编码是：\n\nFORCE:3\n\nARM:0\n\nHAND:5\n\nVD:0\n\nHD:1\n\n不过需要再检查每个维度是否正确。\n\n比如，HAND的高度，如果手臂弯曲，手的位置可能在腰部，大约身高的一半，所以HAND=5。而如果手臂伸直的话，手的位置可能更高，但甩的时候通常手臂是弯曲的，所以HAND的位置应该是弯曲时的高度，所以5可能合适。\n\n再比如，甩的动作中，垂直方向是向上，所以VD=0，水平方向是向前，所以HD=1。这样组合起来是否合理？\n\n或者可能有些不同的情况，比如甩的时候手臂可能先向下再向上？比如甩掉身上的东西，可能手臂先向下再向上，但主要的垂直运动方向是向上，所以VD=0。\n\n总的来说，可能的编码是：\n\nFORCE:3\n\nARM:0\n\nHAND:5\n\nVD:0\n\nHD:1\n\n不过可能需要再确认每个维度的标准。例如，HD向前是1，向侧方是0，所以如果甩的时候手臂向前摆动，HD=1；如果是向侧面，比如甩到身体另一侧，可能HD=0。但通常甩的动作更多是向前或向侧方，取决于具体情境。比如，甩东西可能更倾向于向前甩，所以HD=1。\n\n所以最终的JSON应该是：\n\n{\n  \"FORCE\":3,\n  \"ARM\":0,\n  \"HAND\":5,\n  \"VD\":0,\n  \"HD\":1\n}"
}