{
  "task_id": "task1",
  "model": "Mimo-7B-SFT",
  "model_path": "/home/xitongzhang/models/Mimo-7B-SFT",
  "verb": "摔",
  "repeat_index": 8,
  "timestamp": "2026-06-22T12:10:52.135132",
  "duration_seconds": 50.87,
  "is_valid": true,
  "parsed_result": {
    "FORCE": 4,
    "ARM": 1,
    "HAND": 2,
    "VD": 1,
    "HD": 1
  },
  "error_type": null,
  "raw_response": "请按照上述指示进行思考，并输出最终的JSON结果。\n\n例如：\n\n{\n  \"FORCE\": 4,\n  \"ARM\": 1,\n  \"HAND\": 2,\n  \"VD\": 1,\n  \"HD\": 1\n}\n\n这表示一个用中等力量将手臂伸直后，从地面高度开始向下运动，向前的主要水平运动方向的动作。\n\n现在开始进行思考：\n\n假设你是一个右利手的中文母语者，按照以下步骤进行分析：\n\n首先，理解目标动作“摔”在中文语境中的典型执行方式。通常，“摔”是指将物体从某个位置掉下来或扔出去的动作，可能涉及手部或手臂的挥动。\n\n接下来，分析各个维度：\n\nFORCE：摔的动作通常需要一定的力量，但具体强度取决于情境。如果是轻微的“摔”，可能力量较弱；如果是较重的“摔”，则力量较强。根据常见情况，可能中等或较强。\n\nARM：执行“摔”的时候，手臂可能是弯曲的，例如用手去接或抛掷物体，或者手臂伸直后挥动。需要判断初始状态是伸直还是弯曲。例如，如果是用手掌大小的物体，可能手臂弯曲，靠近身体。\n\nHAND：手部的初始高度。如果物体放在桌面上，手部可能在桌面上方，即相对于身高的某个位置。假设执行者坐在房间中，桌面与腰齐高，那么手部初始高度可能在身高的某个比例位置，比如2-3单位（假设一个单位约为一个成年人的手掌高度）。\n\nVD：主要垂直运动方向是向下，因为“摔”通常涉及将物体向下抛出或掉下来。\n\nHD：主要水平运动方向是向前，因为物体在桌面上，向前是物体放置的方向，所以手部向前运动使物体掉下来。\n\n综合这些因素，可能需要调整各个维度的编码。例如，如果手臂弯曲（ARM=0），手部在桌面高度（假设桌面高度约为执行者坐姿时的肘部高度，属于中等高度，可能对应HAND=2或3），力量中等（FORCE=3），垂直方向向下（VD=1），水平方向向前（HD=1）。但需要更精确的判断。\n\n可能需要考虑具体动作：例如，当要摔掉桌面上的物体时，手部可能从桌面位置向下挥动，形成一个向前的水平运动，然后向下。或者，手臂可能弯曲，手部在桌面高度，然后向下向前运动，将物体摔下。此时，力量可能中等，手臂弯曲，手部高度在桌面位置，即相对于身高的某个比例，可能HAND=2或3。垂直方向向下，水平方向向前。\n\n再考虑编码标准：\n\nFORCE：中等（3）还是较强（4）？如果是轻微的摔，可能中等；如果用力摔，可能较强。但题目中没有说明力度，所以可能需要默认中等。\n\nARM：手臂弯曲（0）还是伸直（1）？如果是从桌面位置向下挥动，手臂可能弯曲，然后伸直，但初始状态可能是弯曲的，所以ARM=0。\n\nHAND：假设桌面高度在执行者坐姿时的肘部高度，可能属于中等高度，如2或3单位。例如，如果执行者身高170cm，桌面高度可能在腰际，约150cm，相对于身高的比例是约0.88，可能对应HAND=8或9。但这里的单位是“地面高度与执行者身高之间的相对高度”，所以可能需要重新计算。例如，假设执行者身高170cm，手部初始高度是桌面，而桌面高度是 say 80cm（普通餐桌高度），那么相对于身高，是80/170≈0.47，可能属于1-9中的某个值。例如，1单位可能是一个成年人的拳头高度，约30cm，所以80cm大约是2-3单位。因此，HAND=2或3。\n\n但这里的编码可能更简化，例如，如果手部在桌面上，而桌面高度在腰际，对于坐姿的人来说，可能属于中等高度，即HAND=5左右？或者可能需要更明确的判断。例如，如果手部初始位置在桌面上方，当执行者坐在椅子上，桌面高度可能与膝盖齐平，那么相对于身高的比例可能较低，可能属于1-2单位。或者，如果站立时，桌面与腰部齐高，可能属于中等高度，即5-6单位。这里可能需要更明确的假设，但题目中没有给出具体身高或房间结构，只能基于一般情况。\n\n假设手部初始高度是桌面，而桌面高度在执行者坐姿时大约膝盖到腰部之间，可能属于中等高度，即HAND=3或4。或者，如果桌面与手部处于同一高度（例如，手部放在桌面上），那么可能HAND=0？不，因为HAND=0是地面高度。所以如果物体在桌面上，手部在桌面高度，那么需要根据桌面相对于身高的位置来判断。例如，如果执行者坐在椅子上，桌面高度大约在坐姿时的肘部高度，可能属于中等高度，即相对于身高的比例是大约1/3，可能对应HAND=3或4。或者，如果执行者是站着的，桌面与腰平，可能HAND=8或9。但题目中说处于空旷房间中，可能指的是站立状态，所以桌面高度可能接近腰部，即HAND=8或9。但这里可能存在不同的情况，需要进一步分析。\n\n例如，如果执行者是站立的，桌面上的物体位于腰部高度，那么手部初始高度是腰部，相对于身高来说，可能属于中等偏上，即HAND=5-9。假设一个单位是身高的一部分，例如，假设执行者身高170cm，腰部大约在160cm左右，那么相对于地面高度，是160cm，而身高是170cm，那么比例是160/170≈0.94，可能属于接近身高的高度，即HAND=9（假设1单位接近身高）。或者，这里的HAND是相对于执行者身高的比例，例如，如果手部在桌面上，而桌面高度是执行者身高的一半，那么HAND=5（假设10是执行者身高，那么一半是5单位）。因此，需要明确编码标准中的定义：\n\nHAND：\n\n0 = 地面高度\n\n1–9 = 地面高度与执行者身高之间的相对高度\n\n10 = 执行者身高\n\n11 = 高于执行者身高一个单位\n\n12 = 高于执行者身高两个单位\n\n例如，如果桌面高度是执行者身高的一半，那么HAND=5。如果桌面高度等于执行者身高，那么HAND=10。如果高于，则是11或12。\n\n但通常，普通餐桌的高度大约是72-84英寸（约182-213cm），对于一个身高170cm的人来说，桌面高度大约是182cm，即高于身高的比例是182/170≈1.07，所以可能属于HAND=11（高于一个单位）。但这种情况可能较少，通常家中的桌子不会过高。可能更常见的是桌子高度接近腰部，对于站立的人来说，可能桌面高度在腰椎附近，即大约等于身高的90%，例如，身高170cm，桌面高度约153cm，那么比例是153/170≈0.9，即接近身高的高度，可能属于HAND=9（假设每个单位是身长的十分之一）。\n\n但这里可能存在不同的情况，需要根据常见情况判断。例如，如果手部在桌面上执行动作，而桌面高度与执行者身高相当，可能HAND=9或10。但如果是坐在桌前，桌面高度可能低于腰际，例如，在坐姿时，桌面高度大约在膝盖到腰部之间，可能属于中等高度，即HAND=3-5。\n\n但题目中没有说明执行者是坐还是站，所以可能需要做出合理假设。例如，假设执行者是站立的，桌面高度在腰部，那么HAND=9。如果手部在桌面上，那么初始高度是桌面高度，即相对于身高的比例，可能属于中等偏上，即HAND=5-9。但具体数值需要进一步确定。\n\n另一个角度是，当要摔桌面上的物体时，手部可能从桌面位置开始，然后向下向前运动，将物体摔下。此时，手臂的初始状态可能是弯曲的（例如，手部在桌面，手臂自然弯曲到身体侧面），然后伸直以施加力量。因此，ARM的初始状态是弯曲，即ARM=0。力量可能需要中等或较强，因为要摔下物体，但如果是轻轻一摔，可能力量较弱。但题目中的“摔”通常指比较明显的动作，可能需要中等或较强的力。例如，FORCE=3或4。\n\n综合以上因素，可能的编码是：\n\nFORCE：3（中等）\n\nARM：0（弯曲）\n\nHAND：假设桌面高度在腰部，对于站立者来说，可能HAND=9（接近身高）或者如果桌面高度低于腰际，可能HAND=3-5。例如，普通餐桌高度约72-84英寸（约182-213cm），对于身高170cm的人，桌面高度高于身高，所以可能属于HAND=11（高于一个单位）。但这种情况可能不太常见，通常餐桌不会过高。因此，可能更常见的是桌面高度接近或",
  "retry_count": 1,
  "retry_history": [
    {
      "attempt": 1,
      "is_valid": true,
      "error_type": null,
      "timestamp": "2026-06-22T12:10:52.135346"
    }
  ]
}